{"rain_total":{"years":30,"start":1991,"end":2020,"unit":"0.1mm","data":{"jan":{"v":3848,"q":8},"feb":{"v":2613,"q":8},"mar":{"v":2233,"q":8},"apr":{"v":1757,"q":8},"may":{"v":1490,"q":8},"jun":{"v":1927,"q":8},"jul":{"v":3451,"q":8},"aug":{"v":2505,"q":8},"sep":{"v":2027,"q":8},"oct":{"v":2400,"q":8},"nov":{"v":3764,"q":8},"dec":{"v":4506,"q":8},"annual":{"v":32520,"q":8}}},"rain_sd":{"years":30,"start":1991,"end":2020,"unit":"0.1mm","data":{"jan":{"v":1077,"q":8},"feb":{"v":799,"q":8},"mar":{"v":621,"q":8},"apr":{"v":633,"q":8},"may":{"v":591,"q":8},"jun":{"v":998,"q":8},"jul":{"v":1781,"q":8},"aug":{"v":1516,"q":8},"sep":{"v":768,"q":8},"oct":{"v":720,"q":8},"nov":{"v":1127,"q":8},"dec":{"v":1168,"q":8},"annual":{"v":3590,"q":8}}},"rain_10pct":{"years":30,"start":1991,"end":2020,"unit":"0.1mm","data":{"jan":{"v":2040,"q":8},"feb":{"v":1180,"q":8},"mar":{"v":950,"q":8},"apr":{"v":390,"q":8},"may":{"v":690,"q":8},"jun":{"v":510,"q":8},"jul":{"v":425,"q":8},"aug":{"v":250,"q":8},"sep":{"v":1105,"q":8},"oct":{"v":1540,"q":8},"nov":{"v":1975,"q":8},"dec":{"v":2500,"q":8},"annual":{"v":24690,"q":8}}},"rain_25pct":{"years":30,"start":1991,"end":2020,"unit":"0.1mm","data":{"jan":{"v":2432,"q":8},"feb":{"v":1545,"q":8},"mar":{"v":1455,"q":8},"apr":{"v":950,"q":8},"may":{"v":827,"q":8},"jun":{"v":882,"q":8},"jul":{"v":1715,"q":8},"aug":{"v":897,"q":8},"sep":{"v":1257,"q":8},"oct":{"v":1657,"q":8},"nov":{"v":2510,"q":8},"dec":{"v":2832,"q":8},"annual":{"v":27082,"q":8}}},"rain_50pct":{"years":30,"start":1991,"end":2020,"unit":"0.1mm","data":{"jan":{"v":3452,"q":8},"feb":{"v":2310,"q":8},"mar":{"v":1830,"q":8},"apr":{"v":1542,"q":8},"may":{"v":1140,"q":8},"jun":{"v":1370,"q":8},"jul":{"v":2355,"q":8},"aug":{"v":1680,"q":8},"sep":{"v":1542,"q":8},"oct":{"v":1972,"q":8},"nov":{"v":3290,"q":8},"dec":{"v":4150,"q":8},"annual":{"v":31110,"q":8}}},"rain_75pct":{"years":30,"start":1991,"end":2020,"unit":"0.1mm","data":{"jan":{"v":4115,"q":8},"feb":{"v":3082,"q":8},"mar":{"v":2662,"q":8},"apr":{"v":2125,"q":8},"may":{"v":1785,"q":8},"jun":{"v":2235,"q":8},"jul":{"v":4140,"q":8},"aug":{"v":2947,"q":8},"sep":{"v":2137,"q":8},"oct":{"v":2600,"q":8},"nov":{"v":3860,"q":8},"dec":{"v":4780,"q":8},"annual":{"v":33950,"q":8}}},"rain_90pct":{"years":30,"start":1991,"end":2020,"unit":"0.1mm","data":{"jan":{"v":5622,"q":8},"feb":{"v":3705,"q":8},"mar":{"v":3030,"q":8},"apr":{"v":2555,"q":8},"may":{"v":2405,"q":8},"jun":{"v":3492,"q":8},"jul":{"v":5830,"q":8},"aug":{"v":4325,"q":8},"sep":{"v":2937,"q":8},"oct":{"v":3075,"q":8},"nov":{"v":5047,"q":8},"dec":{"v":5755,"q":8},"annual":{"v":37555,"q":8}}},"rain_max":{"years":30,"start":1991,"end":2020,"unit":"0.1mm","data":{"jan":{"v":6080,"q":8},"feb":{"v":4130,"q":8},"mar":{"v":3360,"q":8},"apr":{"v":3140,"q":8},"may":{"v":2650,"q":8},"jun":{"v":3840,"q":8},"jul":{"v":7765,"q":8},"aug":{"v":7170,"q":8},"sep":{"v":4320,"q":8},"oct":{"v":5140,"q":8},"nov":{"v":7190,"q":8},"dec":{"v":8205,"q":8},"annual":{"v":39400,"q":8}}},"rain_days_50":{"years":30,"start":1991,"end":2020,"unit":"day","data":{"jan":{"v":7,"q":8},"feb":{"v":3,"q":8},"mar":{"v":1,"q":8},"apr":{"v":3,"q":8},"may":{"v":3,"q":8},"jun":{"v":9,"q":8},"jul":{"v":20,"q":8},"aug":{"v":12,"q":8},"sep":{"v":4,"q":8},"oct":{"v":8,"q":8},"nov":{"v":15,"q":8},"dec":{"v":9,"q":8},"annual":{"v":94,"q":8}}},"rain_days_100":{"years":30,"start":1991,"end":2020,"unit":"day","data":{"jan":{"v":0,"q":8},"feb":{"v":0,"q":8},"mar":{"v":0,"q":8},"apr":{"v":1,"q":8},"may":{"v":0,"q":8},"jun":{"v":4,"q":8},"jul":{"v":11,"q":8},"aug":{"v":7,"q":8},"sep":{"v":2,"q":8},"oct":{"v":2,"q":8},"nov":{"v":5,"q":8},"dec":{"v":3,"q":8},"annual":{"v":35,"q":8}}},"rain_days_200":{"years":30,"start":1991,"end":2020,"unit":"day","data":{"jan":{"v":0,"q":8},"feb":{"v":0,"q":8},"mar":{"v":0,"q":8},"apr":{"v":0,"q":8},"may":{"v":0,"q":8},"jun":{"v":1,"q":8},"jul":{"v":4,"q":8},"aug":{"v":2,"q":8},"sep":{"v":1,"q":8},"oct":{"v":1,"q":8},"nov":{"v":0,"q":8},"dec":{"v":0,"q":8},"annual":{"v":9,"q":8}}},"rain1h_total":{"years":30,"start":1991,"end":2020,"unit":"0.1mm","data":{"jan":{"v":260,"q":8},"feb":{"v":215,"q":8},"mar":{"v":208,"q":8},"apr":{"v":148,"q":8},"may":{"v":129,"q":8},"jun":{"v":126,"q":8},"jul":{"v":157,"q":8},"aug":{"v":127,"q":8},"sep":{"v":143,"q":8},"oct":{"v":163,"q":8},"nov":{"v":202,"q":8},"dec":{"v":248,"q":8},"annual":{"v":2126,"q":8}}},"rain1h_10pct":{"years":30,"start":1991,"end":2020,"unit":"0.1mm","data":{"jan":{"v":220,"q":8},"feb":{"v":130,"q":8},"mar":{"v":120,"q":8},"apr":{"v":80,"q":8},"may":{"v":80,"q":8},"jun":{"v":50,"q":8},"jul":{"v":60,"q":8},"aug":{"v":60,"q":8},"sep":{"v":80,"q":8},"oct":{"v":130,"q":8},"nov":{"v":140,"q":8},"dec":{"v":180,"q":8},"annual":{"v":1860,"q":8}}},"rain1h_25pct":{"years":30,"start":1991,"end":2020,"unit":"0.1mm","data":{"jan":{"v":230,"q":8},"feb":{"v":170,"q":8},"mar":{"v":170,"q":8},"apr":{"v":100,"q":8},"may":{"v":90,"q":8},"jun":{"v":85,"q":8},"jul":{"v":95,"q":8},"aug":{"v":75,"q":8},"sep":{"v":100,"q":8},"oct":{"v":140,"q":8},"nov":{"v":175,"q":8},"dec":{"v":200,"q":8},"annual":{"v":1990,"q":8}}},"rain1h_50pct":{"years":30,"start":1991,"end":2020,"unit":"0.1mm","data":{"jan":{"v":250,"q":8},"feb":{"v":210,"q":8},"mar":{"v":200,"q":8},"apr":{"v":130,"q":8},"may":{"v":120,"q":8},"jun":{"v":110,"q":8},"jul":{"v":135,"q":8},"aug":{"v":105,"q":8},"sep":{"v":130,"q":8},"oct":{"v":150,"q":8},"nov":{"v":190,"q":8},"dec":{"v":235,"q":8},"annual":{"v":2095,"q":8}}},"rain1h_75pct":{"years":30,"start":1991,"end":2020,"unit":"0.1mm","data":{"jan":{"v":280,"q":8},"feb":{"v":235,"q":8},"mar":{"v":230,"q":8},"apr":{"v":175,"q":8},"may":{"v":140,"q":8},"jun":{"v":140,"q":8},"jul":{"v":170,"q":8},"aug":{"v":150,"q":8},"sep":{"v":155,"q":8},"oct":{"v":175,"q":8},"nov":{"v":215,"q":8},"dec":{"v":270,"q":8},"annual":{"v":2180,"q":8}}},"rain1h_90pct":{"years":30,"start":1991,"end":2020,"unit":"0.1mm","data":{"jan":{"v":280,"q":8},"feb":{"v":255,"q":8},"mar":{"v":240,"q":8},"apr":{"v":190,"q":8},"may":{"v":155,"q":8},"jun":{"v":170,"q":8},"jul":{"v":225,"q":8},"aug":{"v":175,"q":8},"sep":{"v":190,"q":8},"oct":{"v":190,"q":8},"nov":{"v":230,"q":8},"dec":{"v":285,"q":8},"annual":{"v":2265,"q":8}}},"rain1h_max":{"years":30,"start":1991,"end":2020,"unit":"0.1mm","data":{"jan":{"v":300,"q":8},"feb":{"v":270,"q":8},"mar":{"v":270,"q":8},"apr":{"v":200,"q":8},"may":{"v":190,"q":8},"jun":{"v":200,"q":8},"jul":{"v":250,"q":8},"aug":{"v":230,"q":8},"sep":{"v":200,"q":8},"oct":{"v":200,"q":8},"nov":{"v":250,"q":8},"dec":{"v":300,"q":8},"annual":{"v":2340,"q":8}}},"rain1h_days":{"years":30,"start":1991,"end":2020,"unit":"day","data":{"jan":{"v":139,"q":8},"feb":{"v":101,"q":8},"mar":{"v":86,"q":8},"apr":{"v":62,"q":8},"may":{"v":55,"q":8},"jun":{"v":52,"q":8},"jul":{"v":86,"q":8},"aug":{"v":68,"q":8},"sep":{"v":68,"q":8},"oct":{"v":77,"q":8},"nov":{"v":117,"q":8},"dec":{"v":152,"q":8},"annual":{"v":1061,"q":8}}},"rain1h_days_10pct":{"years":30,"start":1991,"end":2020,"unit":"day","data":{"jan":{"v":70,"q":8},"feb":{"v":40,"q":8},"mar":{"v":40,"q":8},"apr":{"v":10,"q":8},"may":{"v":20,"q":8},"jun":{"v":10,"q":8},"jul":{"v":10,"q":8},"aug":{"v":0,"q":8},"sep":{"v":30,"q":8},"oct":{"v":50,"q":8},"nov":{"v":60,"q":8},"dec":{"v":70,"q":8},"annual":{"v":900,"q":8}}},"rain1h_days_25pct":{"years":30,"start":1991,"end":2020,"unit":"day","data":{"jan":{"v":90,"q":8},"feb":{"v":55,"q":8},"mar":{"v":45,"q":8},"apr":{"v":25,"q":8},"may":{"v":30,"q":8},"jun":{"v":25,"q":8},"jul":{"v":40,"q":8},"aug":{"v":35,"q":8},"sep":{"v":35,"q":8},"oct":{"v":50,"q":8},"nov":{"v":70,"q":8},"dec":{"v":95,"q":8},"annual":{"v":940,"q":8}}},"rain1h_days_50pct":{"years":30,"start":1991,"end":2020,"unit":"day","data":{"jan":{"v":120,"q":8},"feb":{"v":85,"q":8},"mar":{"v":70,"q":8},"apr":{"v":50,"q":8},"may":{"v":40,"q":8},"jun":{"v":40,"q":8},"jul":{"v":70,"q":8},"aug":{"v":50,"q":8},"sep":{"v":60,"q":8},"oct":{"v":70,"q":8},"nov":{"v":105,"q":8},"dec":{"v":150,"q":8},"annual":{"v":1050,"q":8}}},"rain1h_days_75pct":{"years":30,"start":1991,"end":2020,"unit":"day","data":{"jan":{"v":150,"q":8},"feb":{"v":120,"q":8},"mar":{"v":100,"q":8},"apr":{"v":75,"q":8},"may":{"v":60,"q":8},"jun":{"v":60,"q":8},"jul":{"v":100,"q":8},"aug":{"v":80,"q":8},"sep":{"v":75,"q":8},"oct":{"v":85,"q":8},"nov":{"v":130,"q":8},"dec":{"v":160,"q":8},"annual":{"v":1100,"q":8}}},"rain1h_days_90pct":{"years":30,"start":1991,"end":2020,"unit":"day","data":{"jan":{"v":185,"q":8},"feb":{"v":140,"q":8},"mar":{"v":115,"q":8},"apr":{"v":90,"q":8},"may":{"v":95,"q":8},"jun":{"v":85,"q":8},"jul":{"v":135,"q":8},"aug":{"v":105,"q":8},"sep":{"v":100,"q":8},"oct":{"v":95,"q":8},"nov":{"v":170,"q":8},"dec":{"v":190,"q":8},"annual":{"v":1165,"q":8}}},"rain1h_days_max":{"years":30,"start":1991,"end":2020,"unit":"day","data":{"jan":{"v":210,"q":8},"feb":{"v":160,"q":8},"mar":{"v":160,"q":8},"apr":{"v":110,"q":8},"may":{"v":110,"q":8},"jun":{"v":100,"q":8},"jul":{"v":190,"q":8},"aug":{"v":170,"q":8},"sep":{"v":110,"q":8},"oct":{"v":110,"q":8},"nov":{"v":200,"q":8},"dec":{"v":230,"q":8},"annual":{"v":1180,"q":8}}},"rain1h_days_50mm":{"years":30,"start":1991,"end":2020,"unit":"day","data":{"jan":{"v":36,"q":8},"feb":{"v":17,"q":8},"mar":{"v":11,"q":8},"apr":{"v":16,"q":8},"may":{"v":11,"q":8},"jun":{"v":18,"q":8},"jul":{"v":38,"q":8},"aug":{"v":26,"q":8},"sep":{"v":16,"q":8},"oct":{"v":22,"q":8},"nov":{"v":45,"q":8},"dec":{"v":54,"q":8},"annual":{"v":311,"q":8}}}}